[{"s": "157-fmi-18", "t": "Ошибка 157 FMI 18: диагностика и устранение на КАМАЗ", "i": "💻", "c": "diagnostika-i-oshibki"}, {"s": "154-kpp-kamaz-skhema", "t": "Схема КПП 154 КАМАЗ: устройство, разборка и ремонт", "i": "🔧", "c": "transmissiya-i-kpp"}, {"s": "157-fmi-18-cummins-kamaz", "t": "Ошибка 157 FMI 18 Cummins КАМАЗ: Диагностика и Ремонт", "i": "💻", "c": "diagnostika-i-oshibki"}, {"s": "157-oshibka-kamaz", "t": "Ошибка 157 КАМАЗ: диагностика и устранение неисправности", "i": "💻", "c": "diagnostika-i-oshibki"}, {"s": "154-korobka-kamaz", "t": "Коробка КАМАЗ 154: устройство, схема переключения и ремонт", "i": "🔧", "c": "transmissiya-i-kpp"}, {"s": "157-oshibka-cummins", "t": "Ошибка 157 Cummins: Причины появления и методы устранения", "i": "💻", "c": "diagnostika-i-oshibki"}, {"s": "157fmi-18-oshibka-na-kamaze", "t": "Ошибка 157FMI 18 на КАМАЗ: расшифровка и устранение", "i": "💻", "c": "diagnostika-i-oshibki"}]