[{"s": "benzinovyj-dvigatel-kamaz", "t": "Бензиновый двигатель КамАЗ: Модели, Характеристики и Устройство", "i": "⚙️", "c": "dvigatel-i-tnvd"}, {"s": "benzovoz-kamaz-model", "t": "Технические характеристики и устройство бензовоза КАМАЗ", "i": "🏗️", "c": "spetstekhnika"}, {"s": "bespilotnye-gruzoviki-kamaz", "t": "Беспилотные грузовики КАМАЗ: Технологии, тесты и эксплуатация", "i": "📋", "c": "modeli-i-kharakteristiki"}, {"s": "bespilotnyj-gruzovik-kamaz", "t": "Беспилотный грузовик КАМАЗ: устройство, тесты и внедрение", "i": "📋", "c": "modeli-i-kharakteristiki"}, {"s": "belaz-ryadom-s-kamazom", "t": "БелАЗ рядом с КамАЗом: анализ габаритов и маневров", "i": "🏗️", "c": "spetstekhnika"}, {"s": "belorusskij-kamaz-samyj-bolshoj", "t": "Белорусский КамАЗ: самый большой самосвал МАЗ-7516", "i": "📋", "c": "modeli-i-kharakteristiki"}, {"s": "belaz-na-fone-kamaza", "t": "БелАЗ на фоне КамАЗа: Сравнение карьерных самосвалов", "i": "📋", "c": "modeli-i-kharakteristiki"}, {"s": "belyj-dym-iz-sapuna-kamaz", "t": "Белый дым из сапуна Камаз: причины, диагностика и методы устранения", "i": "⚙️", "c": "dvigatel-i-tnvd"}, {"s": "besshumnye-zamki-na-kamaz", "t": "Бесшумные замки КАМАЗ: Установка, Схема и Регулировка", "i": "🚪", "c": "kabina-i-salon"}, {"s": "belyj-dym-kamaz", "t": "Белый дым из выхлопной трубы КАМАЗ: причины и устранение", "i": "⚙️", "c": "dvigatel-i-tnvd"}, {"s": "bezdiskovye-kolesa-kamaz", "t": "Бездисковые колеса КАМАЗ: конструкция, разбортовка и обслуживание", "i": "🛞", "c": "shiny-i-kolesa"}, {"s": "belyj-dym-iz-vykhlopnoj-truby-kamaz-prichiny", "t": "Белый дым из выхлопной трубы КАМАЗ: причины и устранение", "i": "⚙️", "c": "dvigatel-i-tnvd"}]