[{"s": "nalog-na-kamaz-v-god", "t": "Налог на КАМАЗ в 2026 году: расчет, ставки и способы оплаты", "i": "⛽", "c": "raskhod-i-normy"}, {"s": "napravlyayushchaya-dlya-shtor-kamaz", "t": "Направляющая для штор КАМАЗ: монтаж и регулировка", "i": "🚪", "c": "kabina-i-salon"}, {"s": "nasos-nizkogo-davleniya-kamaz-evro-4", "t": "Насос низкого давления КАМАЗ Евро-4: ремонт и диагностика", "i": "⚙️", "c": "dvigatel-i-tnvd"}, {"s": "nasos-podnyatiya-kabiny-kamaz", "t": "Насос поднятия кабины КАМАЗ: ремонт, диагностика, замена", "i": "🚪", "c": "kabina-i-salon"}, {"s": "nasos-podnyatiya-kuzova-kamaz", "t": "Насос поднятия кузова КАМАЗ: устройство, ремонт, настройка", "i": "🏗️", "c": "spetstekhnika"}, {"s": "nasos-gura-kamaz-evro-4", "t": "Насос ГУР КамАЗ Евро 4: Диагностика, Ремонт, Замена", "i": "🚜", "c": "khodovaya-i-rulevoe"}, {"s": "nabit-nomer-na-ramu", "t": "Как набить номер на раму: технология восстановления маркировки", "i": "📁", "c": null}, {"s": "nasos-podkachki-kamaz-evro", "t": "Насос подкачки топлива КАМАЗ Евро: устройство, проверка и ремонт", "i": "⚙️", "c": "dvigatel-i-tnvd"}, {"s": "nado-li-zalivat-maslo-v-maslyanyj-filtr-pri-zamene-masla-v-dvigatele", "t": "Заливать ли масло в фильтр при замене: правила для КАМАЗ", "i": "⚙️", "c": "dvigatel-i-tnvd"}, {"s": "nachalo-proizvodstva-kamaz", "t": "Запуск производства КАМАЗ: этапы сборки двигателя и шасси", "i": "🏗️", "c": "spetstekhnika"}, {"s": "nasos-podkachivayushchij-kamaz", "t": "Подкачивающий насос КАМАЗ: устройство, регулировка и замена", "i": "⚙️", "c": "dvigatel-i-tnvd"}, {"s": "nasos-toplivnyj-ruchnoj-podkachki-kamaz", "t": "Ручной насос подкачки топлива Камаз: устройство, регулировка и ремонт", "i": "⚙️", "c": "dvigatel-i-tnvd"}, {"s": "nastrojka-tnvd-kamaz-740", "t": "Настройка ТНВД КАМАЗ 740: Регулировка, параметры и допуски", "i": "⚙️", "c": "dvigatel-i-tnvd"}, {"s": "nanesenie-vin-nomera-na-rame", "t": "Нанесение VIN на раму грузовика: технология и требования", "i": "💻", "c": "diagnostika-i-oshibki"}, {"s": "nasos-gur-ural-4320-s-dvigatelem-yamz-238", "t": "Насос ГУР Урал 4320 (ЯМЗ 238): устройство, регулировка и ремонт", "i": "🚜", "c": "khodovaya-i-rulevoe"}, {"s": "napryazhenie-bortovoj-seti-kamaz", "t": "Напряжение бортовой сети КАМАЗ: нормы, диагностика и устранение неисправностей", "i": "⚡", "c": "elektrooborudovanie"}, {"s": "na-akkumulyatore-odna-banka-ne-zaryazhaetsya-chto-delat", "t": "Одна банка аккумулятора не заряжается: причины и методы восстановления", "i": "⚡", "c": "elektrooborudovanie"}, {"s": "nasos-omyvatelya-gudit-no-ne-bryzgaet", "t": "Насос омывателя гудит, но не брызгает: причины и ремонт", "i": "⚡", "c": "elektrooborudovanie"}, {"s": "na-gazeli-gorit-krasnyj-chek-i-stop", "t": "Горит красный чек и стоп на Газели: причины и устранение", "i": "💻", "c": "diagnostika-i-oshibki"}, {"s": "nakachka-kolesa-vzryvom", "t": "Накачка колеса взрывом: технология и техника безопасности", "i": "🛞", "c": "shiny-i-kolesa"}, {"s": "nakonechnik-poperechnoj-rulevoj-tyagi-kamaz-6520", "t": "Замена наконечника поперечной рулевой тяги КАМАЗ 6520: Инструкция", "i": "📁", "c": null}, {"s": "nasos-podema-kuzova-kamaz-6520", "t": "Насос подъема кузова КАМАЗ 6520: ремонт, схема и регулировка", "i": "🏗️", "c": "spetstekhnika"}, {"s": "na-kakom-toplive-rabotaet-kamaz", "t": "На каком топливе работает КАМАЗ: дизель, газ и экологические классы", "i": "⚙️", "c": "dvigatel-i-tnvd"}, {"s": "nasos-podema-kuzova-kamaz-5511", "t": "Гидросистема подъема кузова КАМАЗ 5511: устройство и ремонт насоса", "i": "🏗️", "c": "spetstekhnika"}, {"s": "nastrojka-spidometra-kamaz", "t": "Настройка спидометра КАМАЗ: калибровка, датчики и ремонт", "i": "⚡", "c": "elektrooborudovanie"}, {"s": "nastrojka-zazhiganiya-kamaz-evro-1", "t": "Регулировка УОЗ Камаз Евро-1: Инструкция по ТНВД ЯЗДА", "i": "⚙️", "c": "dvigatel-i-tnvd"}, {"s": "nastrojka-ratsii-megadzhet-3031m-turbo-na-15-kanal", "t": "Настройка рации Мегаджет 3031М Турбо: 15 канал и сетка", "i": "⚡", "c": "elektrooborudovanie"}, {"s": "nadpis-kamaz-na-oblitsovku", "t": "Установка надписи КАМАЗ на облицовку: инструкция и тюнинг", "i": "🎨", "c": "tyuning-i-dorabotki"}, {"s": "nakonechnik-poperechnoj-rulevoj-tyagi-kamaz-43118", "t": "Замена наконечника рулевой тяги КАМАЗ 43118: Инструкция", "i": "🚜", "c": "khodovaya-i-rulevoe"}, {"s": "nastrojka-ratsii-optim-piligrim-na-dalnost", "t": "Настройка рации Optim Pilgrim: увеличение дальности связи", "i": "⚡", "c": "elektrooborudovanie"}, {"s": "nasos-rulevogo-upravleniya-kamaz", "t": "Насос рулевого управления КАМАЗ: диагностика, регулировка и замена", "i": "🚜", "c": "khodovaya-i-rulevoe"}, {"s": "na-kamaz-kakaya-kategoriya-prav-nuzhna", "t": "Какая категория прав нужна на КАМАЗ: полный разбор категорий B, C, D, E", "i": "📋", "c": "modeli-i-kharakteristiki"}, {"s": "na-kakom-zazhiganii-greetsya-dvigatel", "t": "На каком зажигании греть двигатель КАМАЗ: режимы и нормы", "i": "⚙️", "c": "dvigatel-i-tnvd"}, {"s": "nadpis-top-na-porshnevykh-koltsakh-pravilnost-ustanovki", "t": "Правильная установка поршневых колец: маркировка TOP и ориентация", "i": "⚙️", "c": "dvigatel-i-tnvd"}, {"s": "nagruzka-na-os-kamaz-65115", "t": "Нагрузка на ось КАМАЗ 65115: нормы, регулировка, допустимый вес", "i": "📋", "c": "modeli-i-kharakteristiki"}, {"s": "narezat-rezbu-v-bloke-dvigatelya", "t": "Восстановление резьбы в блоке двигателя КАМАЗ: технологии и допуски", "i": "⚙️", "c": "dvigatel-i-tnvd"}, {"s": "nasos-vysokogo-davleniya-kamaz-evro-5", "t": "Насос высокого давления Камаз Евро 5: диагностика и настройка", "i": "⚙️", "c": "dvigatel-i-tnvd"}, {"s": "nastrojka-klapanov-kamaz", "t": "Регулировка клапанов Камаз: зазоры, схема и порядок", "i": "⚙️", "c": "dvigatel-i-tnvd"}, {"s": "namotka-spidometra-kamaz", "t": "Намотка спидометра КАМАЗ: инструкция, приборы и схемы", "i": "⚡", "c": "elektrooborudovanie"}, {"s": "nasos-nizkogo-davleniya-kamaz-740", "t": "Насос низкого давления КАМАЗ 740: устройство, ремонт, регулировка", "i": "⚙️", "c": "dvigatel-i-tnvd"}, {"s": "nalog-na-kamaz-260-l-s-v-god", "t": "Налог на КАМАЗ 260 л.с.: расчет и льготы 2026", "i": "📋", "c": "modeli-i-kharakteristiki"}, {"s": "nashivki-na-borta-kamaz", "t": "Нашивки на борта Камаз: установка и требования", "i": "🎨", "c": "tyuning-i-dorabotki"}, {"s": "na-skolko-zatyagivat-stupichnuyu-gajku", "t": "Момент затяжки ступичной гайки: таблица и правила", "i": "🚜", "c": "khodovaya-i-rulevoe"}, {"s": "nabivka-nomera-ramy", "t": "Набивка номера рамы: технология восстановления маркировки", "i": "📁", "c": null}, {"s": "napravlyayushchie-gbts-kamaz", "t": "Направляющие ГБЦ КАМАЗ: размеры, установка и допустимый износ", "i": "⚙️", "c": "dvigatel-i-tnvd"}, {"s": "napryamuyu-ne-krutit-starter", "t": "Стартер не крутит: диагностика и ремонт КАМАЗ своими руками", "i": "⚡", "c": "elektrooborudovanie"}, {"s": "nastrojka-ratsii-megajet", "t": "Настройка рации MegaJet: частоты, CTCSS и пошаговая инструкция", "i": "⚡", "c": "elektrooborudovanie"}, {"s": "nasos-omyvatelya-kamaz-54901", "t": "Замена насоса омывателя КАМАЗ 54901: схема, коды ошибок, установка", "i": "⚡", "c": "elektrooborudovanie"}, {"s": "nasos-podema-kuzova-kamaz-65115-kpp-zf", "t": "Насос подъема кузова КАМАЗ 65115 (КПП ZF): устройство, ремонт", "i": "🏗️", "c": "spetstekhnika"}, {"s": "nakladki-kolodok-kamaz", "t": "Накладки колодок КАМАЗ: виды, артикулы и замена", "i": "🛑", "c": "tormoznaya-sistema"}, {"s": "natyazhitel-remnya-kamaz-kamminz", "t": "Замена натяжителя ремня Камминз: Инструкция для Камаз", "i": "⚙️", "c": "dvigatel-i-tnvd"}, {"s": "nasos-toplivnyj-kamaz-kamminz", "t": "Топливный насос Камминз КамАЗ: устройство, диагностика и регулировка", "i": "⚙️", "c": "dvigatel-i-tnvd"}, {"s": "na-pritsepe-ne-rabotayut-svetovye-pribory-kakoj-shtraf", "t": "Не работают фары прицепа: штрафы и причины неисправности", "i": "⚡", "c": "elektrooborudovanie"}, {"s": "nakladka-dveri-kamaz-5490", "t": "Замена и регулировка накладки двери КАМАЗ 5490: Инструкция", "i": "🚪", "c": "kabina-i-salon"}, {"s": "nasos-maslyanyj-kamaz-kamminz-6isbe", "t": "Насос масляный Камминз 6ISBe: устройство, замена и диагностика", "i": "⚙️", "c": "dvigatel-i-tnvd"}, {"s": "nasos-avtonomki-kamaz", "t": "Топливный насос автономки КамАЗ: диагностика, замена и регулировка", "i": "⚙️", "c": "dvigatel-i-tnvd"}, {"s": "natyazhnoj-rolik-kamaz-kamminz", "t": "Натяжной ролик Камминз ISF: Замена, Артикул, Момент затяжки", "i": "⚙️", "c": "dvigatel-i-tnvd"}, {"s": "na-kholostykh-net-zaryadki-a-na-oborotakh-est", "t": "Нет зарядки на холостых оборотах: диагностика генератора КАМАЗ", "i": "⚡", "c": "elektrooborudovanie"}, {"s": "nasos-vodyanoj-kamaz-5320", "t": "Насос водяной КАМАЗ 5320: замена, признаки поломки, артикулы", "i": "⚙️", "c": "dvigatel-i-tnvd"}, {"s": "na-kamaz-kakie-prava-nuzhny", "t": "Какие права нужны для КАМАЗа: категории C, CE и классы E", "i": "📁", "c": null}, {"s": "nado-li-pritirat-klapana-na-novoj-gbts", "t": "Притирка клапанов на новой ГБЦ: нужно ли делать и как проверить", "i": "⚙️", "c": "dvigatel-i-tnvd"}, {"s": "nasos-gura-yamz-238", "t": "Насос ГУР ЯМЗ 238: диагностика, регулировка и ремонт", "i": "🚜", "c": "khodovaya-i-rulevoe"}, {"s": "nasos-nsh-50-kamaz", "t": "Насос НШ 50 на КАМАЗ: характеристики, установка и ремонт", "i": "📁", "c": null}, {"s": "nastrojka-stsepleniya-kamaz", "t": "Настройка сцепления КАМАЗ: Регулировка привода и зазоров", "i": "🔧", "c": "transmissiya-i-kpp"}, {"s": "nasos-gur-kamaz-6520-evro-4", "t": "Насос ГУР КамАЗ 6520 Евро 4: устройство, диагностика и замена", "i": "🚜", "c": "khodovaya-i-rulevoe"}, {"s": "nasos-predpuskovoj-prokachki-topliva-kamaz", "t": "Насос предпусковой прокачки топлива КАМАЗ: устройство, ремонт", "i": "⚙️", "c": "dvigatel-i-tnvd"}, {"s": "nasos-gura-kamaz-65115", "t": "Насос ГУР КамАЗ 65115: устройство, регулировка и ремонт", "i": "🚜", "c": "khodovaya-i-rulevoe"}, {"s": "naroshchennye-borta-na-samosvale", "t": "Нарощенные борта на самосвал: конструкция, установка и правила", "i": "🏗️", "c": "spetstekhnika"}, {"s": "nakladka-bampera-kamaz-43118", "t": "Накладка бампера КАМАЗ 43118: выбор, установка и замена", "i": "📁", "c": null}, {"s": "nakladki-na-bamper-kamaz", "t": "Накладки на бампер КАМАЗ: выбор, установка и защита от ударов", "i": "🎨", "c": "tyuning-i-dorabotki"}, {"s": "nasos-na-manipulyator", "t": "Гидронасос на манипулятор КАМАЗ: устройство, ремонт, замена", "i": "🏗️", "c": "spetstekhnika"}, {"s": "nakonechnik-tyagi-tnvd-kamaz", "t": "Наконечник тяги ТНВД Камаз: замена, диагностика и размеры", "i": "⚙️", "c": "dvigatel-i-tnvd"}, {"s": "nasos-gur-kamaz-65115-cummins", "t": "Насос ГУР Камаз 65115 Cummins: Ремонт, замена и диагностика", "i": "🚜", "c": "khodovaya-i-rulevoe"}, {"s": "na-kakoj-baze-sdelan-kamaz", "t": "На какой базе сделан КАМАЗ: платформы, рамы и узлы", "i": "📋", "c": "modeli-i-kharakteristiki"}, {"s": "nasos-gura-kamaz-skhema", "t": "Насос ГУР КАМАЗ: схема подключения, устройство и ремонт", "i": "🚜", "c": "khodovaya-i-rulevoe"}, {"s": "nasos-dozator-kamaz-evro-5", "t": "Насос-дозатор КАМАЗ Евро 5: устройство, диагностика и регулировка", "i": "⚙️", "c": "dvigatel-i-tnvd"}, {"s": "nasos-gur-kamaz-53501", "t": "Насос ГУР КАМАЗ 53501: Устройство, Ремонт и Замена", "i": "🚜", "c": "khodovaya-i-rulevoe"}, {"s": "nasos-toplivnyj-kamaz-evro-4", "t": "Топливный насос КАМАЗ Евро 4: устройство, диагностика и регулировка", "i": "⚙️", "c": "dvigatel-i-tnvd"}, {"s": "nado-li-regulirovat-klapana-posle-zameny-prokladki-gbts", "t": "Регулировка клапанов после замены прокладки ГБЦ: нужно ли?", "i": "⚙️", "c": "dvigatel-i-tnvd"}, {"s": "nado-li-smazyvat-ftoroplastovye-vtulki", "t": "Смазка фторопластовых втулок: нужно ли и чем обрабатывать", "i": "🔧", "c": "transmissiya-i-kpp"}, {"s": "nastrojka-ratsii-megadzhet-350-na-kanal-dalnobojshchikov", "t": "Настройка рации Мегаджет 350: каналы дальнобойщиков", "i": "📁", "c": null}, {"s": "nakonechnik-prodolnoj-tyagi-kamaz", "t": "Наконечник продольной тяги КАМАЗ: замена, артикулы, регулировка", "i": "🚜", "c": "khodovaya-i-rulevoe"}, {"s": "nazvanie-voennogo-kamaza", "t": "Название военного КАМАЗа: маркировка, индексация и классификация", "i": "📋", "c": "modeli-i-kharakteristiki"}, {"s": "nabivka-nomera-na-ramu-avtomobilya", "t": "Набивка номера на раму грузовика: технология и требования", "i": "📁", "c": null}, {"s": "nabor-otvertok-kamaz", "t": "Набор отверток КАМАЗ: виды, размеры и применение", "i": "📁", "c": null}, {"s": "nakachat-koleso-kamaz", "t": "Как правильно накачать колесо Камаз: давление и нормы", "i": "🛞", "c": "shiny-i-kolesa"}, {"s": "nasos-kom-kamaz-korobka-zf", "t": "Насос Ком КАМАЗ ZF: устройство, замена, регулировка", "i": "🚜", "c": "khodovaya-i-rulevoe"}, {"s": "nakonechnik-poperechnoj-tyagi-kamaz-43118", "t": "Замена наконечника поперечной тяги КАМАЗ 43118: Инструкция", "i": "🚜", "c": "khodovaya-i-rulevoe"}, {"s": "nasos-mocheviny-kamaz", "t": "Насос мочевины КАМАЗ: диагностика, устройство и ремонт", "i": "⚙️", "c": "dvigatel-i-tnvd"}, {"s": "nasos-ruchnoj-podkachki-dizelnogo-topliva-kamaz", "t": "Ручной насос подкачки топлива Камаз: устройство, замена, ремонт", "i": "⚙️", "c": "dvigatel-i-tnvd"}, {"s": "nazvanie-filma-drift-na-kamaze", "t": "Фильм Дрифт на КамАЗе: технические аспекты и реализация", "i": "🎬", "c": "media-i-kultura"}, {"s": "narastit-borta-na-samosval", "t": "Как нарастить борта на самосвал: технологии и расчеты", "i": "🎨", "c": "tyuning-i-dorabotki"}, {"s": "na-skolko-nyutonov-zakruchivat-kolesa", "t": "Момент затяжки колесных гаек КАМАЗ: таблица и правила", "i": "🛞", "c": "shiny-i-kolesa"}, {"s": "naekhal-na-koleso", "t": "Наехал на колесо: диагностика и ремонт подвески КАМАЗ", "i": "🚜", "c": "khodovaya-i-rulevoe"}, {"s": "nasos-dlya-podema-kabiny-kamaz", "t": "Насос подъема кабины КАМАЗ: ремонт, устройство и регулировка", "i": "🚪", "c": "kabina-i-salon"}, {"s": "natyazhnoj-rolik-remnya-kompressora-yamz-238", "t": "Натяжной ролик ремня ЯМЗ-238: устройство, замена, регулировка", "i": "⚙️", "c": "dvigatel-i-tnvd"}, {"s": "nastrojka-klapanov-yamz-238", "t": "Регулировка клапанов ЯМЗ 238: порядок и зазоры", "i": "⚙️", "c": "dvigatel-i-tnvd"}, {"s": "nastrojka-ratsii-megajet-300", "t": "Настройка рации MegaJet 300: частоты, CTCSS, Squelch", "i": "⚡", "c": "elektrooborudovanie"}, {"s": "nastoyashchij-nomer-kamaza-iz-dalnobojshchikov", "t": "Как узнать реальный пробег Камаза: методы проверки для дальнобойщиков", "i": "💻", "c": "diagnostika-i-oshibki"}, {"s": "nakidka-na-sidene-kamaz", "t": "Накидка на сиденье КАМАЗ: виды, выбор и установка своими руками", "i": "🚪", "c": "kabina-i-salon"}, {"s": "na-kamaze-propalo-stseplenie-v-chem-prichina", "t": "Пропало сцепление на КамАЗе: причины и диагностика", "i": "🔧", "c": "transmissiya-i-kpp"}, {"s": "napravlyayushchie-klapanov-kamaz-740", "t": "Направляющие клапанов КАМАЗ 740: размеры, дефектовка и замена", "i": "⚙️", "c": "dvigatel-i-tnvd"}, {"s": "nastrojka-tnvd-kamaz", "t": "Настройка ТНВД Камаз: регулировка циклового и УОТ", "i": "⚙️", "c": "dvigatel-i-tnvd"}, {"s": "naplavka-klemm-akkumulyatora", "t": "Наплавка клемм аккумулятора: технология и материалы", "i": "⚡", "c": "elektrooborudovanie"}, {"s": "nasadka-na-glushitel-kamaz", "t": "Насадка на глушитель Камаз: виды, установка и влияние на звук", "i": "🎨", "c": "tyuning-i-dorabotki"}, {"s": "nasos-gur-kamaz-kamminz-6isbe-65115", "t": "Насос ГУР Камаз Камминз 6ISBe: Диагностика и ремонт 65115", "i": "🚜", "c": "khodovaya-i-rulevoe"}, {"s": "nasos-omyvatelya-lobovogo-stekla-kamaz", "t": "Насос омывателя КАМАЗ: диагностика, замена и схема подключения", "i": "⚡", "c": "elektrooborudovanie"}, {"s": "nasos-rulevoj-kamaz", "t": "Насос рулевой Камаз: устройство, регулировка и ремонт ГУР", "i": "🚜", "c": "khodovaya-i-rulevoe"}, {"s": "nasos-vodyanoj-kamaz-kamminz", "t": "Водяной насос Камминз ISF 2.8 и 3.8: устройство, замена, неисправности", "i": "⚙️", "c": "dvigatel-i-tnvd"}, {"s": "nado-li-zalivat-maslo-v-filtr-pri-zamene-masla", "t": "Заливать ли масло в фильтр при замене: инструкция для КАМАЗ", "i": "⚙️", "c": "dvigatel-i-tnvd"}, {"s": "natyazhnoj-rolik-kompressora-yamz-238", "t": "Натяжной ролик компрессора ЯМЗ 238: замена, дефектовка и установка", "i": "⚙️", "c": "dvigatel-i-tnvd"}, {"s": "navigator-dlya-gruzovykh-avtomobilej-na-android-skachat-besplatno-na-russkom-yazyke", "t": "Грузовой навигатор для Андроид: скачать бесплатно на русском", "i": "📁", "c": null}, {"s": "nagruzka-na-os-kamaz-65115-samosval", "t": "Нагрузка на ось КАМАЗ 65115: нормы, распределение и контроль", "i": "📋", "c": "modeli-i-kharakteristiki"}, {"s": "nastrojka-ratsii-megadzhet-350", "t": "Настройка радиостанции MegaJet MJ-350: пошаговая инструкция", "i": "⚡", "c": "elektrooborudovanie"}, {"s": "nakonechnik-rulevoj-kamaz-4308", "t": "Замена рулевого наконечника Камаз 4308: Инструкция и момент затяжки", "i": "🚜", "c": "khodovaya-i-rulevoe"}, {"s": "nasos-podkachki-kamaz-740", "t": "Насос подкачки топлива КАМАЗ 740: устройство, регулировка и ремонт", "i": "⚙️", "c": "dvigatel-i-tnvd"}, {"s": "natyazhitel-remnya-kamaz-evro-4", "t": "Натяжитель ремня Камаз Евро 4: устройство, диагностика, замена", "i": "⚙️", "c": "dvigatel-i-tnvd"}, {"s": "na-kakom-toplive-ezdit-kamaz", "t": "Топливо для КАМАЗ: виды дизеля, требования и нормы расхода", "i": "⚙️", "c": "dvigatel-i-tnvd"}, {"s": "na-kamaze-ne-vklyuchaetsya", "t": "Не включается КАМАЗ: диагностика причин и запуск двигателя", "i": "💻", "c": "diagnostika-i-oshibki"}, {"s": "nasos-mocheviny-kamaz-evro-5", "t": "Насос мочевины Камаз Евро-5: устройство, диагностика и ремонт", "i": "⚙️", "c": "dvigatel-i-tnvd"}, {"s": "na-vysokikh-oborotakh-zagoraetsya-lampochka-zaryadki-akkumulyatora", "t": "Горит лампа зарядки на высоких оборотах: диагностика генератора", "i": "⚡", "c": "elektrooborudovanie"}, {"s": "nakladki-tormoznykh-kolodok-kamaz", "t": "Накладки тормозных колодок Камаз: замена, артикулы и регулировка", "i": "🛑", "c": "tormoznaya-sistema"}, {"s": "namotka-spidometra-kamaz-evro-2", "t": "Намотка спидометра Камаз Евро-2: Инструкция и схемы", "i": "💻", "c": "diagnostika-i-oshibki"}, {"s": "napravlyayushchaya-klapana-kamaz-740", "t": "Направляющая клапана Камаз 740: размеры, замена, допуски", "i": "⚙️", "c": "dvigatel-i-tnvd"}, {"s": "nasos-gur-ural-4320-s-dvigatelem-kamaz-740", "t": "Насос ГУР Урал 4320 с двигателем КАМАЗ 740: устройство, ремонт", "i": "🚜", "c": "khodovaya-i-rulevoe"}, {"s": "nasos-podkachki-topliva-kamaz", "t": "Насос подкачки топлива КАМАЗ: устройство, диагностика и замена", "i": "⚙️", "c": "dvigatel-i-tnvd"}, {"s": "natyazhka-remnya-generatora-kamaz", "t": "Натяжка ремня генератора КАМАЗ: нормы и инструкции", "i": "⚡", "c": "elektrooborudovanie"}, {"s": "nasos-podkachki-topliva-kamaz-ruchnoj", "t": "Ручной насос подкачки топлива КАМАЗ: устройство, ремонт и прокачка", "i": "⚙️", "c": "dvigatel-i-tnvd"}, {"s": "nasos-tsirkulyatsionnyj-kamaz", "t": "Циркуляционный насос КАМАЗ: устройство, диагностика и замена", "i": "⚙️", "c": "dvigatel-i-tnvd"}, {"s": "na-pritsepe-ne-rabotayut-svetovye-pribory", "t": "Не горят габариты прицепа: диагностика и ремонт проводки", "i": "⚡", "c": "elektrooborudovanie"}, {"s": "na-massu-idet-plyus-ili-minus", "t": "На массу идет плюс или минус: схемы КАМАЗ", "i": "⚡", "c": "elektrooborudovanie"}, {"s": "na-platone-morgaet-krasnyj-indikator-chek-4-raza", "t": "Мигает индикатор чек на КАМАЗе: расшифровка и устранение", "i": "💻", "c": "diagnostika-i-oshibki"}, {"s": "nabor-instrumentov-mastak-otzyvy", "t": "Набор инструментов Мастак: отзывы, обзоры и совместимость", "i": "📁", "c": null}, {"s": "nastrojka-ratsii-mj-300", "t": "Настройка рации MJ-300: пошаговая инструкция и частоты", "i": "⚡", "c": "elektrooborudovanie"}, {"s": "nastrojka-zazhiganiya-yamz-236", "t": "Настройка зажигания ЯМЗ 236: порядок работы цилиндров и регулировка", "i": "⚙️", "c": "dvigatel-i-tnvd"}, {"s": "nazhimaesh-na-tormoz-i-slyshno-vozdukh", "t": "Свист воздуха при торможении: диагностика пневмосистемы КАМАЗ", "i": "🛑", "c": "tormoznaya-sistema"}, {"s": "nachalo-stroitelstva-kamaza", "t": "Начало строительства Камаза: этапы сборки рамы и двигателя", "i": "🏗️", "c": "spetstekhnika"}, {"s": "nasos-tnvd-kamaz-evro-4", "t": "ТНВД КамАЗ Евро 4: Устройство, регулировка и диагностика Common Rail", "i": "⚙️", "c": "dvigatel-i-tnvd"}, {"s": "nasos-toplivnyj-kamaz-evro-5", "t": "Топливный насос КамАЗ Евро-5: Устройство, Диагностика и Ремонт", "i": "⚙️", "c": "dvigatel-i-tnvd"}, {"s": "nasos-na-pzhd-kamaz", "t": "Насос ПЖД Камаз: устройство, неисправности, ремонт и регулировка", "i": "⚙️", "c": "dvigatel-i-tnvd"}, {"s": "narezka-rezby-v-soske-kamery", "t": "Нарезка резьбы в соске камеры: инструкция, метчики, размеры", "i": "🛞", "c": "shiny-i-kolesa"}, {"s": "nasos-podema-kuzova-kamaz-65115", "t": "Насос подъема кузова Камаз 65115: устройство, ремонт, замена", "i": "🏗️", "c": "spetstekhnika"}, {"s": "nado-li-nalivat-maslo-v-filtr-pri-zamene-masla-v-dvigatele", "t": "Нужно ли заливать масло в фильтр: инструкция для КАМАЗ", "i": "⚙️", "c": "dvigatel-i-tnvd"}, {"s": "nastrojka-ratsii-optima-piligrim", "t": "Настройка рации Оптима Пилигрим: полная инструкция", "i": "⚡", "c": "elektrooborudovanie"}, {"s": "nasos-kommon-rejl-kamaz", "t": "Ремонт Common Rail КамАЗ: диагностика, ошибки и настройка ТНВД", "i": "⚙️", "c": "dvigatel-i-tnvd"}, {"s": "nalog-na-kamaz", "t": "Налог на КАМАЗ: ставки, льготы и расчет для грузовиков", "i": "📁", "c": null}, {"s": "nasos-maslyanyj-kamaz-5320", "t": "Масляный насос КАМАЗ 5320: устройство, разборка и регулировка", "i": "⚙️", "c": "dvigatel-i-tnvd"}, {"s": "navodki-ot-generatora", "t": "Наводки от генератора КАМАЗ: поиск, диагностика и устранение", "i": "⚡", "c": "elektrooborudovanie"}, {"s": "nasos-gur-kamaz-skhema", "t": "Схема насоса ГУР КамАЗ: устройство, разборка и регулировка", "i": "🚜", "c": "khodovaya-i-rulevoe"}, {"s": "nasos-perekachki-topliva-kamaz", "t": "Насос перекачки топлива КАМАЗ: устройство, ремонт и замена", "i": "⚙️", "c": "dvigatel-i-tnvd"}, {"s": "nasos-vysokogo-davleniya-kamaz", "t": "Насос высокого давления КАМАЗ: устройство, диагностика и регулировка", "i": "⚙️", "c": "dvigatel-i-tnvd"}, {"s": "nastrojka-radiostantsii-megadzhet-300", "t": "Настройка радиостанции Мегаджет 300: Полная инструкция", "i": "⚡", "c": "elektrooborudovanie"}, {"s": "nakidka-na-panel-kamaz", "t": "Накидка на панель КАМАЗ: выбор, установка и уход за покрытием", "i": "🚪", "c": "kabina-i-salon"}, {"s": "nastrojka-klapanov-kamaz-740", "t": "Регулировка клапанов Камаз 740: порядок, зазоры, моменты", "i": "⚙️", "c": "dvigatel-i-tnvd"}, {"s": "nasos-predpuskovoj-kamaz", "t": "Предпусковой насос Камаз: устройство, замена и прокачка", "i": "⚙️", "c": "dvigatel-i-tnvd"}, {"s": "nasos-tnvd-kamaz-bosh", "t": "Насос ТНВД Камаз Бош: ремонт, регулировка и диагностика", "i": "⚙️", "c": "dvigatel-i-tnvd"}, {"s": "nadut-shiny-mashiny", "t": "Как правильно накачать шины: давление, нормы и инструкция", "i": "🛞", "c": "shiny-i-kolesa"}, {"s": "nakladka-na-bamper-kamaz-evro-2", "t": "Накладка на бампер КАМАЗ Евро 2: установка и выбор защиты", "i": "🎨", "c": "tyuning-i-dorabotki"}, {"s": "nasos-predpuskovoj-podkachki-topliva-kamaz", "t": "Насос предпусковой подкачки топлива КАМАЗ: устройство, ремонт", "i": "⚙️", "c": "dvigatel-i-tnvd"}, {"s": "nasos-vodyanoj-kamaz-740-evro-4", "t": "Водяной насос КамАЗ 740 Евро-4: Устройство, Артикул, Замена", "i": "⚙️", "c": "dvigatel-i-tnvd"}, {"s": "nakonechnik-tyagi-gaza-kamaz-evro", "t": "Замена наконечника тяги газа КАМАЗ Евро: Инструкция и каталожные номера", "i": "🔧", "c": "transmissiya-i-kpp"}, {"s": "napravlyayushchie-dlya-shtor-v-gruzovik-kamaz", "t": "Направляющие для штор КАМАЗ: монтаж, виды и регулировка", "i": "🚪", "c": "kabina-i-salon"}, {"s": "nasos-gur-kamaz-65115", "t": "Насос ГУР КамАЗ 65115: устройство, диагностика, замена и регулировка", "i": "🚜", "c": "khodovaya-i-rulevoe"}, {"s": "nasos-toplivopodkachivayushchij-kamaz-740", "t": "Насос топливоподкачивающий КАМАЗ 740: устройство, регулировка и ремонт", "i": "⚙️", "c": "dvigatel-i-tnvd"}, {"s": "natyazhenie-remnya-generatora-kamaz", "t": "Натяжение ремня генератора КамАЗ: нормы и инструкции", "i": "⚡", "c": "elektrooborudovanie"}, {"s": "nakladka-na-bamper-kamaz-evro", "t": "Накладка на бампер КАМАЗ Евро: установка, виды, ремонт", "i": "🎨", "c": "tyuning-i-dorabotki"}, {"s": "nadutaya-kamera-ot-kamaza", "t": "Надутая камера Камаза: причины вздутия и методы ремонта", "i": "🛞", "c": "shiny-i-kolesa"}, {"s": "nasos-podema-kuzova-kamaz", "t": "Насос подъема кузова КАМАЗ: устройство, ремонт и настройка", "i": "🏗️", "c": "spetstekhnika"}, {"s": "nakladki-na-fary-kamaz", "t": "Накладки на фары КАМАЗ: выбор, установка и тюнинг оптики", "i": "🎨", "c": "tyuning-i-dorabotki"}, {"s": "napajka-klemmy-na-akkumulyatore", "t": "Ремонт АКБ КАМАЗ: напайка клеммы свинцовым припоем", "i": "⚡", "c": "elektrooborudovanie"}, {"s": "nastroit-ratsiyu-megadzhet-300", "t": "Настройка рации Мегаджет 300: пошаговая инструкция", "i": "⚡", "c": "elektrooborudovanie"}, {"s": "na-kamaze-ne-zapuskaetsya-avtonomka", "t": "Не запускается автономка на КамАЗе: диагностика и ремонт", "i": "⚡", "c": "elektrooborudovanie"}, {"s": "nakonechnik-kulisy-kamaz-65115", "t": "Наконечник кулисы Камаз 65115: замена, артикулы и диагностика", "i": "🔧", "c": "transmissiya-i-kpp"}, {"s": "na-generatore-w", "t": "Генератор КАМАЗ W: Ремонт, Схема, Регулировка", "i": "⚡", "c": "elektrooborudovanie"}, {"s": "nakladki-tormoznye-kamaz-65115-perednie", "t": "Тормозные накладки КАМАЗ 65115 передние: замена и параметры", "i": "🛑", "c": "tormoznaya-sistema"}, {"s": "narezka-rezby-pod-zolotnik", "t": "Нарезка резьбы под золотник: технология, инструменты и допуски", "i": "📁", "c": null}, {"s": "nado-li-zalivat-maslo-v-filtr-pri-zamene-masla-v-dvigatele", "t": "Нужно ли лить масло в фильтр при замене: инструкция КАМАЗ", "i": "⚙️", "c": "dvigatel-i-tnvd"}, {"s": "nalog-na-kamaz-260-l-s", "t": "Налог на КАМАЗ 260 л.с.: расчет, льготы и ставки", "i": "📁", "c": null}, {"s": "nasos-gura-kamaz-starogo-obraztsa", "t": "Насос ГУР КамАЗ старого образца: ремонт, регулировка и замена", "i": "🚜", "c": "khodovaya-i-rulevoe"}, {"s": "nasos-nsh-na-kamaz", "t": "Насос НШ на КАМАЗ: устройство, установка, неисправности и регулировка", "i": "🏗️", "c": "spetstekhnika"}, {"s": "nasos-gidrousilitelya-yamz-238", "t": "Насос ГУР ЯМЗ 238: устройство, регулировка и ремонт", "i": "🚜", "c": "khodovaya-i-rulevoe"}, {"s": "nasos-podkachki-kamaz", "t": "Насос подкачки КАМАЗ: устройство, неисправности и замена", "i": "⚙️", "c": "dvigatel-i-tnvd"}, {"s": "na-chem-ezdit-kamaz", "t": "На чем ездит КамАЗ: устройство колесных пар и трансмиссии", "i": "🚜", "c": "khodovaya-i-rulevoe"}, {"s": "na-chto-vliyaet-gruppa-porshnej", "t": "Группа поршней: влияние на мощность и ресурс КАМАЗ", "i": "⚙️", "c": "dvigatel-i-tnvd"}, {"s": "napravlenie-vrashcheniya-ventilyatora-okhlazhdeniya-dvigatelya", "t": "Направление вращения вентилятора КАМАЗ: установка и схема", "i": "⚙️", "c": "dvigatel-i-tnvd"}, {"s": "nasos-podema-kuzova-kamaz-6520-kpp-zf", "t": "Насос подъема кузова КАМАЗ 6520: устройство, ремонт, регулировка", "i": "🏗️", "c": "spetstekhnika"}, {"s": "nastrojka-ratsii-megadzhet-300", "t": "Настройка рации Мегаджет 300: частоты и каналы", "i": "⚡", "c": "elektrooborudovanie"}, {"s": "nado-li-nalivat-maslo-v-maslyanyj-filtr-pered-ustanovkoj", "t": "Нужно ли наливать масло в фильтр: полная инструкция", "i": "⚙️", "c": "dvigatel-i-tnvd"}, {"s": "na-kholodnuyu-ne-dymit-a-na-goryachuyu-dymit", "t": "Двигатель дымит на горячую: причины и устранение", "i": "⚙️", "c": "dvigatel-i-tnvd"}, {"s": "nasos-gidravlicheskij-dlya-manipulyatora", "t": "Гидравлический насос для манипулятора: виды, неисправности, выбор", "i": "🏗️", "c": "spetstekhnika"}, {"s": "na-kakikh-avto-steklyannye-fary", "t": "На каких авто стеклянные фары: справочник КАМАЗ и грузовиков", "i": "⚡", "c": "elektrooborudovanie"}, {"s": "nasos-tsirkulyatsionnyj-pzhd", "t": "Насос циркуляционный ПЖД: устройство, схема и ремонт", "i": "⚡", "c": "elektrooborudovanie"}, {"s": "nasos-ruchnoj-podkachki-kamaz", "t": "Ручной насос подкачки КАМАЗ: устройство, замена и ремонт", "i": "📁", "c": null}, {"s": "naplavit-klemmu-na-akkumulyatore-svoimi-rukami", "t": "Как наплавить клемму на аккумуляторе своими руками", "i": "⚡", "c": "elektrooborudovanie"}, {"s": "nakonechnik-rulevoj-kamaz-43118", "t": "Наконечник рулевой Камаз 43118: замена, артикулы, диагностика", "i": "🚜", "c": "khodovaya-i-rulevoe"}, {"s": "natyazhnoj-rolik-remnya-pompy-yamz-238", "t": "Натяжной ролик ремня помпы ЯМЗ 238: замена и регулировка", "i": "⚙️", "c": "dvigatel-i-tnvd"}, {"s": "na-goryachuyu-propadaet-stseplenie", "t": "Проваливается сцепление на горячую: диагностика и ремонт КАМАЗ", "i": "🔧", "c": "transmissiya-i-kpp"}, {"s": "nastrojka-avtomobilnoj-ratsii-svoimi-rukami-na-15-kanal", "t": "Настройка 15 канала рации: инструкция для дальнобойщиков", "i": "⚡", "c": "elektrooborudovanie"}, {"s": "nasos-gura-kamaz-6520-evro-4", "t": "Насос ГУР КАМАЗ 6520 Евро 4: диагностика, замена и регулировка", "i": "🚜", "c": "khodovaya-i-rulevoe"}, {"s": "nado-li-nalivat-maslo-v-filtr-pri-zamene", "t": "Нужно ли лить масло в фильтр при замене: полная инструкция", "i": "⚙️", "c": "dvigatel-i-tnvd"}, {"s": "na-mtz-82-tyazhelo-krutitsya-rul-prichina", "t": "Тяжело крутится руль на МТЗ 82: причины и устранение", "i": "🚜", "c": "khodovaya-i-rulevoe"}, {"s": "nagruzka-na-osi-kamaza", "t": "Нагрузка на оси КАМАЗ: нормы, расчет и распределение", "i": "📋", "c": "modeli-i-kharakteristiki"}, {"s": "nastrojka-zazhiganiya-kamaz", "t": "Настройка зажигания КамАЗ: регулировка угла опережения ТНВД", "i": "⚙️", "c": "dvigatel-i-tnvd"}, {"s": "na-kamaze-propalo-stseplenie", "t": "Пропало сцепление на КАМАЗе: причины, поиск неисправностей и ремонт", "i": "🔧", "c": "transmissiya-i-kpp"}, {"s": "napravlyayushchie-golovok-kamaz", "t": "Направляющие головок КамАЗ: устройство, регулировка и ремонт", "i": "⚙️", "c": "dvigatel-i-tnvd"}, {"s": "nasos-gura-kamaz-5320-skhema", "t": "Схема ГУР КАМАЗ 5320: устройство, регулировка и ремонт насоса", "i": "🚜", "c": "khodovaya-i-rulevoe"}, {"s": "natyazhitel-remnya-kamaz-kamminz-6isbe", "t": "Натяжитель ремня Камаз Камминз 6ISBe: устройство, регулировка, замена", "i": "⚙️", "c": "dvigatel-i-tnvd"}, {"s": "napravlenie-ventilyatora-okhlazhdeniya", "t": "Направление вращения вентилятора охлаждения: как установить правильно", "i": "⚙️", "c": "dvigatel-i-tnvd"}, {"s": "nasos-gur-kamaz-evro-4", "t": "Насос ГУР КАМАЗ Евро-4: диагностика, ремонт и замена", "i": "🚜", "c": "khodovaya-i-rulevoe"}, {"s": "napolnoe-pokrytie-kamaz", "t": "Напольное покрытие КАМАЗ: выбор, монтаж и уход за кабиной", "i": "🚪", "c": "kabina-i-salon"}, {"s": "na-platone-gorit-krasnyj-indikator", "t": "Горит красный индикатор на КАМАЗе: диагностика и устранение", "i": "💻", "c": "diagnostika-i-oshibki"}, {"s": "nasos-gur-kamaz-65117", "t": "Насос ГУР КАМАЗ 65117: устройство, регулировка и ремонт", "i": "🚜", "c": "khodovaya-i-rulevoe"}, {"s": "nasos-gura-kamaz-evro-5", "t": "Насос ГУР КАМАЗ Евро 5: устройство, регулировка и ремонт", "i": "🚜", "c": "khodovaya-i-rulevoe"}, {"s": "naplavit-klemmu-na-akkumulyatore", "t": "Как наплавить клемму на аккумуляторе: Технология и инструкция", "i": "⚡", "c": "elektrooborudovanie"}, {"s": "nasos-tsirkulyatsionnyj-pzhd-14-ts", "t": "Насос циркуляционный ПЖД 14 ТС: устройство, схема и ремонт", "i": "⚙️", "c": "dvigatel-i-tnvd"}, {"s": "napryazhenie-s-generatora-na-akkumulyator-kakoe-dolzhno-byt", "t": "Нормы напряжения генератора на аккумулятор КАМАЗ: стандарты и диагностика", "i": "⚡", "c": "elektrooborudovanie"}, {"s": "nasos-toplivnyj-nizkogo-davleniya-kamaz-740", "t": "Топливный насос низкого давления КАМАЗ 740: устройство, ремонт, регулировка", "i": "⚙️", "c": "dvigatel-i-tnvd"}, {"s": "na-kakoe-rasstoyanie-beret-ratsiya", "t": "Дальность радиосвязи: факторы, расчеты и нормы", "i": "⚡", "c": "elektrooborudovanie"}, {"s": "napravlenie-potoka-vozdukha-ventilyatora-radiatora-avto", "t": "Направление потока воздуха вентилятора КАМАЗ: установка и схемы", "i": "📁", "c": null}, {"s": "naklejka-osel-na-kamaz", "t": "Наклейка осел на КАМАЗ: технологии, материалы и монтаж", "i": "🎨", "c": "tyuning-i-dorabotki"}, {"s": "nastrojka-megadzhet-300", "t": "Настройка Мегаджет 300: полное руководство по установке", "i": "⚡", "c": "elektrooborudovanie"}, {"s": "nastrojka-vremeni-na-takhografe", "t": "Настройка времени на тахографе: подробная инструкция", "i": "⚡", "c": "elektrooborudovanie"}, {"s": "na-korpuse-avtomobilya-plyus-ili-minus", "t": "На корпусе автомобиля плюс или минус: масса и питание", "i": "⚡", "c": "elektrooborudovanie"}, {"s": "nado-li-zalivat-maslo-v-filtr-pri-zamene", "t": "Масло в фильтр при замене: лить или нет? Техника", "i": "⚙️", "c": "dvigatel-i-tnvd"}, {"s": "nalog-na-260-l-s", "t": "Налог на двигатель 260 л. с.: расчет и ставки", "i": "⛽", "c": "raskhod-i-normy"}, {"s": "nasos-podema-kabiny-kamaz-43118", "t": "Насос подъема кабины КАМАЗ 43118: устройство, ремонт", "i": "🚪", "c": "kabina-i-salon"}, {"s": "nasos-dlya-kmu-3-tonny", "t": "Насос для КМУ 3 тонны: выбор, установка и настройка", "i": "🏗️", "c": "spetstekhnika"}, {"s": "nabit-nomer-na-shassi", "t": "Как набить номер на шасси: технологии и правила маркировки", "i": "📁", "c": null}, {"s": "nagrevaetsya-tormoznoj-baraban-granta", "t": "Почему греется тормозной барабан на Гранте: причины и ремонт", "i": "🛑", "c": "tormoznaya-sistema"}, {"s": "nastrojka-zazhiganiya-kamaz-740", "t": "Регулировка зажигания КАМАЗ 740: Угол опережения и метки", "i": "⚙️", "c": "dvigatel-i-tnvd"}, {"s": "nadut-kolesa-mashiny", "t": "Как правильно накачать колеса грузовика КАМАЗ: давление и нормы", "i": "🛞", "c": "shiny-i-kolesa"}, {"s": "nakidki-na-sidenya-kamaz", "t": "Накидки на сиденья КАМАЗ: выбор, установка и уход", "i": "🚪", "c": "kabina-i-salon"}]