[{"s": "tochki-smazki-kamaz-43118-vezdekhod-maslenki", "t": "Точки смазки КАМАЗ 43118 вездеход: схема и инструкция по обслуживанию", "i": "🚜", "c": "khodovaya-i-rulevoe"}, {"s": "tonar-kamaz-neo", "t": "Тонар КАМАЗ НЕО: настройка, диагностика и ремонт", "i": "⚡", "c": "elektrooborudovanie"}, {"s": "toplivnaya-sistema-kamaz-43118", "t": "Топливная система КАМАЗ 43118: устройство, диагностика, ремонт", "i": "⚙️", "c": "dvigatel-i-tnvd"}, {"s": "toplivnaya-sistema-kamaz-740", "t": "Топливная система КАМАЗ 740: устройство, неисправности, ремонт", "i": "⚙️", "c": "dvigatel-i-tnvd"}, {"s": "toplivnyj-filtr-kamaz-43114", "t": "Топливный фильтр КамАЗ 43114: замена, выбор, диагностика", "i": "⚙️", "c": "dvigatel-i-tnvd"}, {"s": "toplivnyj-filtr-kamaz-5320", "t": "Топливный фильтр КАМАЗ-5320: замена, выбор, диагностика", "i": "⚙️", "c": "dvigatel-i-tnvd"}, {"s": "toplivnyj-nasos-kamaz-evro-5-kommon-rejl", "t": "Топливный насос КАМАЗ Евро-5 Common Rail: ремонт и диагностика", "i": "⚙️", "c": "dvigatel-i-tnvd"}, {"s": "toplivnyj-nasos-ot-kamaza", "t": "Топливный насос КамАЗ: устройство, ремонт, регулировка", "i": "⚙️", "c": "dvigatel-i-tnvd"}, {"s": "tormoznaya-lyagushka-kamaz", "t": "Тормозная лягушка КАМАЗ: устройство, регулировка и ремонт", "i": "🛑", "c": "tormoznaya-sistema"}, {"s": "tormoznoj-mekhanizm-kamaz", "t": "Тормозной механизм КАМАЗ: устройство, ремонт, регулировка", "i": "🛑", "c": "tormoznaya-sistema"}, {"s": "tormoznoj-tsilindr-kamaz", "t": "Тормозной цилиндр КАМАЗ: устройство, ремонт, неисправности", "i": "🛑", "c": "tormoznaya-sistema"}, {"s": "tornado-na-baze-kamaza", "t": "Торнадо на базе КамАЗа: техническая инструкция по сборке и эксплуатации", "i": "🏗️", "c": "spetstekhnika"}, {"s": "torsion-ot-kamaza", "t": "Торсион КамАЗ: ремонт, замена и регулировка своими руками", "i": "🚜", "c": "khodovaya-i-rulevoe"}, {"s": "toplivnye-trubki-kamaz-evro-5-komon-rejl", "t": "Топливные трубки Камаз Евро 5: Схема, размеры и замена", "i": "⚙️", "c": "dvigatel-i-tnvd"}, {"s": "toplivnyj-bak-na-kamaz-250-litrov", "t": "Топливный бак КАМАЗ 250 литров: характеристики, установка и ремонт", "i": "📁", "c": null}, {"s": "tormoznaya-sistema-kamaz-53501", "t": "Тормозная система КАМАЗ 53501: устройство, схемы и регулировка", "i": "🛑", "c": "tormoznaya-sistema"}, {"s": "tormoznoj-kran-kamaz-skhema-podklyucheniya", "t": "Тормозной кран КАМАЗ: схема подключения и монтаж", "i": "🛑", "c": "tormoznaya-sistema"}, {"s": "toplivnyj-bak-kamaz-4310", "t": "Топливный бак Камаз 4310: объем, устройство и обслуживание", "i": "📋", "c": "modeli-i-kharakteristiki"}, {"s": "toplivnyj-zabornik-kamaz", "t": "Топливный заборник КамАЗ: устройство, замена и доработки", "i": "⚙️", "c": "dvigatel-i-tnvd"}, {"s": "tormoznaya-sistema-kamaz-53212", "t": "Тормозная система КАМАЗ 53212: устройство, схема и регулировка", "i": "🛑", "c": "tormoznaya-sistema"}, {"s": "toplivozabornik-kamaz-4310", "t": "Топливозаборник КАМАЗ 4310: устройство, замена, ремонт", "i": "⚙️", "c": "dvigatel-i-tnvd"}, {"s": "toplivnye-filtry-na-kamaz", "t": "Замена топливных фильтров Камаз: виды, артикулы и этапы", "i": "⚙️", "c": "dvigatel-i-tnvd"}, {"s": "toplivnyj-filtr-kamaz-kamens", "t": "Топливный фильтр Камаз Камминс: выбор, замена и диагностика", "i": "⚙️", "c": "dvigatel-i-tnvd"}, {"s": "tormoznoj-baraban-perednij-kamaz", "t": "Тормозной барабан передний КамАЗ: размеры, замена, ресурс", "i": "🛑", "c": "tormoznaya-sistema"}, {"s": "tormoznoj-kran-kamaz-neo", "t": "Тормозной кран КАМАЗ НЕО: Устройство, регулировка, схема", "i": "🛑", "c": "tormoznaya-sistema"}, {"s": "tormoznoj-kulak-kamaz-65115", "t": "Тормозной кулак КАМАЗ 65115: устройство, регулировка и замена", "i": "🛑", "c": "tormoznaya-sistema"}, {"s": "tormoznaya-sistema-kamaz-skhema", "t": "Тормозная система Камаз: схема, устройство и настройка", "i": "🛑", "c": "tormoznaya-sistema"}, {"s": "tolshchina-diska-stsepleniya-kamaz-dvukhdiskovoe", "t": "Толщина диска сцепления КАМАЗ двухдисковое: нормы и допуски", "i": "🔧", "c": "transmissiya-i-kpp"}, {"s": "tormoznaya-sistema-kamaz-43-10", "t": "Тормозная система КАМАЗ 4310: Устройство, Схема и Ремонт", "i": "🛑", "c": "tormoznaya-sistema"}, {"s": "toplivnaya-sistema-kamaz-evro-2", "t": "Топливная система Камаз Евро-2: устройство, ТНВД и регулировка", "i": "⚙️", "c": "dvigatel-i-tnvd"}, {"s": "toplivnaya-sistema-kamaz-evro-3", "t": "Топливная система Камаз Евро 3: устройство, диагностика, регулировка ТНВД", "i": "⚙️", "c": "dvigatel-i-tnvd"}, {"s": "toplivnyj-nasos-kamaz-740-ustrojstvo", "t": "Устройство ТНВД Камаз 740: схема, разбор и регулировка", "i": "⚙️", "c": "dvigatel-i-tnvd"}, {"s": "tormoznaya-sistema-kamaz-5350", "t": "Тормозная система Камаз 5350: схема, устройство и регулировка", "i": "🛑", "c": "tormoznaya-sistema"}, {"s": "toplivnaya-sistema-kamaz-5350", "t": "Топливная система Камаз 5350: устройство, регулировка ТНВД и диагностика", "i": "⚙️", "c": "dvigatel-i-tnvd"}, {"s": "toplivnaya-trubka-kamaz-evro-5-na-klipsakh", "t": "Топливная трубка КамАЗ Евро-5: замена, артикулы, установка на клипсах", "i": "⚙️", "c": "dvigatel-i-tnvd"}, {"s": "tormoznaya-sistema-kamaz-43118-vezdekhod", "t": "Тормозная система КАМАЗ 43118: Схема, устройство, регулировка", "i": "🛑", "c": "tormoznaya-sistema"}, {"s": "tormoznaya-sistema-kamaz-55111", "t": "Тормозная система КАМАЗ 55111: устройство, схема, ремонт", "i": "🛑", "c": "tormoznaya-sistema"}, {"s": "toplivnaya-sistema-kamaz-740-skhema", "t": "Схема топливной системы Камаз 740: устройство, ТНВД, форсунки", "i": "⚙️", "c": "dvigatel-i-tnvd"}, {"s": "toplivnyj-nasos-kamaz-65115", "t": "Топливный насос КамАЗ 65115: устройство, диагностика, ремонт и регулировка", "i": "⚙️", "c": "dvigatel-i-tnvd"}, {"s": "tochki-smazki-kamaz-5350", "t": "Карта смазки Камаз 5350: точки, интервалы, нормы", "i": "🚜", "c": "khodovaya-i-rulevoe"}, {"s": "toplivnaya-sistema-kamaz-6520", "t": "Топливная система Камаз 6520: устройство, регулировка ТНВД, ошибки", "i": "⚙️", "c": "dvigatel-i-tnvd"}, {"s": "tormoznye-kolodki-kamaz-65117", "t": "Тормозные колодки КАМАЗ 65117: артикулы, замена и регулировка", "i": "🛑", "c": "tormoznaya-sistema"}, {"s": "tormoznaya-sistema-kamaz-4308", "t": "Тормозная система КАМАЗ 4308: устройство, схемы и ремонт", "i": "🛑", "c": "tormoznaya-sistema"}, {"s": "toplivnaya-sistema-kamaz-5490", "t": "Топливная система КАМАЗ 5490: устройство, диагностика, ошибки", "i": "⚙️", "c": "dvigatel-i-tnvd"}, {"s": "tormoznaya-sistema-kamaz-evro-5", "t": "Тормозная система Камаз Евро-5: устройство, схемы, неисправности", "i": "🛑", "c": "tormoznaya-sistema"}, {"s": "tormoznye-kolodki-kamaz-4308-diskovye", "t": "Тормозные колодки КАМАЗ 4308: замена, артикулы, регулировка", "i": "🛑", "c": "tormoznaya-sistema"}, {"s": "toplivnaya-trubka-kamaz-evro-5", "t": "Топливная трубка КамАЗ Евро-5: виды, замена и диагностика", "i": "⚙️", "c": "dvigatel-i-tnvd"}, {"s": "tormoznaya-sistema-kamaz-evro", "t": "Тормозная система КАМАЗ Евро: Устройство, диагностика, ремонт", "i": "🛑", "c": "tormoznaya-sistema"}, {"s": "toplivnyj-filtr-tonkoj-ochistki-kamaz-evro-5", "t": "Топливный фильтр Камаз Евро 5: выбор, замена и диагностика", "i": "⚙️", "c": "dvigatel-i-tnvd"}, {"s": "toplivnyj-nasos-nizkogo-davleniya-kamaz-evro-5", "t": "Топливный насос низкого давления КамАЗ Евро-5: Устройство и ремонт", "i": "⚙️", "c": "dvigatel-i-tnvd"}, {"s": "tormoznoj-kran-kamaz-5511", "t": "Тормозной кран КАМАЗ 5511: устройство, регулировка и ремонт", "i": "🛑", "c": "tormoznaya-sistema"}, {"s": "tormoznaya-kamera-perednyaya-kamaz-65115", "t": "Тормозная камера Камаз 65115: устройство, замена и регулировка", "i": "🛑", "c": "tormoznaya-sistema"}, {"s": "tormoznaya-sistema-kamaz-65115", "t": "Тормозная система КАМАЗ 65115: устройство, схема, ремонт", "i": "🛑", "c": "tormoznaya-sistema"}, {"s": "toplivnaya-rampa-kamaz", "t": "Топливная рампа КАМАЗ: устройство, давление, регулировка", "i": "⚙️", "c": "dvigatel-i-tnvd"}, {"s": "tormoznaya-sistema-kamaz-4310-skhema", "t": "Схема тормозной системы КАМАЗ 4310: устройство и ремонт", "i": "🛑", "c": "tormoznaya-sistema"}, {"s": "tormoznaya-treshchetka-kamaz-ustrojstvo", "t": "Устройство тормозной трещотки Камаз: принцип работы и регулировка", "i": "🛑", "c": "tormoznaya-sistema"}, {"s": "tormoznoj-kran-kamaz-5320", "t": "Тормозной кран КАМАЗ 5320: устройство, регулировка и ремонт", "i": "🛑", "c": "tormoznaya-sistema"}, {"s": "tormoznoj-raspredelitel-kamaz", "t": "Тормозной распределитель КАМАЗ: устройство, регулировка, неисправности", "i": "🛑", "c": "tormoznaya-sistema"}, {"s": "tolshchina-diska-stsepleniya-kamaz-odnodiskovoe-evro", "t": "Толщина диска сцепления КАМАЗ Евро: нормы, износ, допуски", "i": "🔧", "c": "transmissiya-i-kpp"}, {"s": "tormoznaya-sistema-kamaz-5511-s-nazvaniyami-mekhanizmov-skhema-tsvetnaya", "t": "Тормозная система КАМАЗ 5511: схема, устройство и ремонт", "i": "🛑", "c": "tormoznaya-sistema"}, {"s": "tormoznaya-sistema-zil-130-kamazovskaya", "t": "Тормозная система ЗИЛ 130: установка пневматики КамАЗ", "i": "🛑", "c": "tormoznaya-sistema"}, {"s": "tormoznaya-sistema-kamaz-43118", "t": "Тормозная система КАМАЗ 43118: устройство, схемы, регулировка", "i": "🛑", "c": "tormoznaya-sistema"}, {"s": "tormoznaya-sistema-kamaz-5320-skhema", "t": "Схема тормозной системы КАМАЗ 5320: устройство, узлы и регулировка", "i": "🛑", "c": "tormoznaya-sistema"}, {"s": "tormoznaya-sistema-kamaz-5350-skhema", "t": "Схема тормозной системы КамАЗ 5350: устройство и ремонт", "i": "🛑", "c": "tormoznaya-sistema"}, {"s": "tormoznoj-put-kamaza", "t": "Тормозной путь КАМАЗа: Нормы, расчет и таблица", "i": "🛑", "c": "tormoznaya-sistema"}, {"s": "toplivnaya-sistema-kamaz-kamminz-6isbe", "t": "Топливная система Камаз Камминз 6ISBe: устройство и ремонт", "i": "⚙️", "c": "dvigatel-i-tnvd"}, {"s": "toplivnyj-nasos-kamaz-5320", "t": "Топливный насос КАМАЗ 5320: Устройство, Ремонт, Регулировка", "i": "⚙️", "c": "dvigatel-i-tnvd"}, {"s": "toplivnyj-nasos-kamaz-evro-4-kommon-rejl", "t": "Топливный насос КамАЗ Евро 4 Common Rail: диагностика, устройство", "i": "⚙️", "c": "dvigatel-i-tnvd"}, {"s": "tormoznaya-sistema-kamaz-5490", "t": "Тормозная система КАМАЗ 5490: устройство, схема, регулировка", "i": "🛑", "c": "tormoznaya-sistema"}, {"s": "tormoza-kamaz-5320", "t": "Тормоза КАМАЗ 5320: устройство, регулировка и ремонт", "i": "🛑", "c": "tormoznaya-sistema"}, {"s": "tormoznaya-sistema-kamaz-53-20", "t": "Тормозная система Камаз 5320: Схема, Неисправности, Ремонт", "i": "🛑", "c": "tormoznaya-sistema"}, {"s": "tormoznye-diski-kamaz-5490-zadnie", "t": "Задние тормозные диски Камаз 5490: Артикул, замена, диагностика", "i": "🛑", "c": "tormoznaya-sistema"}, {"s": "tormoznaya-sistema-kamaz-43114", "t": "Тормозная система КАМАЗ 43114: схема, устройство, регулировка", "i": "🛑", "c": "tormoznaya-sistema"}, {"s": "toplivnaya-sistema-kamaz-skhema", "t": "Топливная система КамАЗ: схема, устройство и диагностика", "i": "⚙️", "c": "dvigatel-i-tnvd"}, {"s": "toplivnaya-sistema-kamaz-evro-3-tnvd-bosh", "t": "Топливная система КамАЗ Евро 3 ТНВД Bosch: Устройство и Диагностика", "i": "⚙️", "c": "dvigatel-i-tnvd"}, {"s": "toplivnaya-sistema-kamaz-evro-5-skhema", "t": "Топливная система Камаз Евро 5: схема, устройство и диагностика", "i": "⚙️", "c": "dvigatel-i-tnvd"}, {"s": "toplivnaya-sistema-kamaz-evro-5", "t": "Топливная система Камаз Евро 5: устройство, диагностика и ремонт", "i": "⚙️", "c": "dvigatel-i-tnvd"}, {"s": "toplivnaya-pompa-kamaz", "t": "Топливная помпа КамАЗ: устройство, регулировка и ремонт", "i": "⚙️", "c": "dvigatel-i-tnvd"}, {"s": "tormoznaya-sistema-na-kamaze", "t": "Тормозная система КАМАЗ: устройство, схемы и регулировка", "i": "🛑", "c": "tormoznaya-sistema"}, {"s": "toplivnaya-sistema-kamaz-k5", "t": "Топливная система Камаз К5: устройство, диагностика и регулировка", "i": "⚙️", "c": "dvigatel-i-tnvd"}, {"s": "tormoznoj-kran-kamaz-skhema", "t": "Тормозной кран КАМАЗ: схема, устройство и регулировка", "i": "🛑", "c": "tormoznaya-sistema"}, {"s": "tormoznye-diski-kamaz-4308", "t": "Тормозные диски КАМАЗ 4308: артикулы, размеры, замена", "i": "🛑", "c": "tormoznaya-sistema"}, {"s": "toplivnyj-filtr-tonkoj-ochistki-kamaz-740", "t": "Топливный фильтр Камаз 740: Замена и Диагностика", "i": "⚙️", "c": "dvigatel-i-tnvd"}, {"s": "tormoznaya-sistema-kamaz-5320-skhema-tsvetnaya-s-nazvaniyami-mekhanizmov-i-printsip-dejstviya", "t": "Тормозная система КАМАЗ 5320: схема, устройство и принцип работы", "i": "🛑", "c": "tormoznaya-sistema"}, {"s": "toplivnye-filtra-na-kamaz-evro-2", "t": "Топливный фильтр КАМАЗ Евро 2: замена, схема и особенности", "i": "⚙️", "c": "dvigatel-i-tnvd"}, {"s": "torpeda-kamaz-65115", "t": "Торпеда Камаз 65115: схема, разборка и замена", "i": "⚡", "c": "elektrooborudovanie"}, {"s": "tormoznaya-sistema-avtomobilya-kamaz", "t": "Тормозная система КАМАЗ: устройство, схемы и ремонт", "i": "🛑", "c": "tormoznaya-sistema"}, {"s": "tormoznaya-sistema-kamaz-43118-skhema", "t": "Тормозная система КАМАЗ 43118: Схема, устройство и регулировка", "i": "🛑", "c": "tormoznaya-sistema"}, {"s": "tormoznaya-sistema-zil-130-kamazovskaya-skhema-s-opisaniem", "t": "Схема тормозной системы ЗИЛ 130 с компрессором КАМАЗ", "i": "🛑", "c": "tormoznaya-sistema"}, {"s": "torsion-kabiny-kamaz-razmery", "t": "Торсион кабины КАМАЗ: размеры, артикулы, замена", "i": "🚪", "c": "kabina-i-salon"}, {"s": "toplivo-dlya-kamaza", "t": "Топливо для КамАЗа: нормы, стандарты и требования ГОСТ", "i": "⛽", "c": "raskhod-i-normy"}, {"s": "tormoznaya-sistema-kamaz-5490-skhema", "t": "Схема тормозной системы КАМАЗ 5490: устройство и диагностика", "i": "🛑", "c": "tormoznaya-sistema"}, {"s": "toplivnaya-sistema-kamaz-evro-4-common-rail-skhema-ustrojstva", "t": "Топливная система Камаз Евро 4 Common Rail: схема и устройство", "i": "⚙️", "c": "dvigatel-i-tnvd"}, {"s": "tormoznaya-sistema-kamaz-5320", "t": "Тормозная система КамАЗ 5320: Схема, Устройство и Ремонт", "i": "🛑", "c": "tormoznaya-sistema"}, {"s": "toplivnaya-sistema-kamaz-evro-5-kommon-rejl", "t": "Топливная система Камаз Евро 5 Common Rail: устройство и диагностика", "i": "⚙️", "c": "dvigatel-i-tnvd"}, {"s": "toplivnaya-trubka-kamaz-evro-5-na-klipsakh-ot-filtra-k-nasosu", "t": "Замена топливной трубки КАМАЗ Евро 5: клипсы, фильтр, ТНВД", "i": "⚙️", "c": "dvigatel-i-tnvd"}, {"s": "tochki-shpritsevaniya-kamaz-43118", "t": "Точки шприцевания Камаз 43118: полная карта и схема смазки", "i": "📁", "c": null}, {"s": "toplivoprovod-kamaz-evro-5", "t": "Топливопровод Камаз Евро 5: устройство, схема, замена и ремонт", "i": "⚙️", "c": "dvigatel-i-tnvd"}, {"s": "tormoznoj-val-kamaz", "t": "Тормозной вал КАМАЗ: устройство, неисправности и замена", "i": "🛑", "c": "tormoznaya-sistema"}, {"s": "toplivnaya-rampa-kamaz-cummins-6isbe", "t": "Топливная рампа КАМАЗ Cummins 6ISBe: устройство, регулировка, коды ошибок", "i": "⚙️", "c": "dvigatel-i-tnvd"}, {"s": "toplivnyj-nasos-nizkogo-davleniya-kamaz-evro-4", "t": "Топливный насос низкого давления Камаз Евро-4: устройство, диагностика", "i": "⚙️", "c": "dvigatel-i-tnvd"}, {"s": "toplivnaya-sistema-kamaz-5320", "t": "Топливная система Камаз 5320: устройство, ТНВД, регулировка", "i": "⚙️", "c": "dvigatel-i-tnvd"}, {"s": "tormoznaya-lyagushka-kamaz-5320", "t": "Тормозная лягушка КамАЗ 5320: замена и регулировка", "i": "🛑", "c": "tormoznaya-sistema"}, {"s": "tormoznaya-sistema-kamaz-65115-skhema-tsvetnaya", "t": "Схема тормозной системы Камаз 65115: цветная и подробная", "i": "🛑", "c": "tormoznaya-sistema"}, {"s": "tormoznoj-kran-kamaz-ustrojstvo", "t": "Тормозной кран КАМАЗ: устройство, схема и регулировка", "i": "🛑", "c": "tormoznaya-sistema"}, {"s": "toplivnye-filtra-na-kamaz", "t": "Замена топливных фильтров на КамАЗ: виды, артикулы и инструкция", "i": "⚙️", "c": "dvigatel-i-tnvd"}, {"s": "tolshchina-diska-stsepleniya-kamaz", "t": "Толщина диска сцепления КАМАЗ: нормы износа и замена", "i": "🔧", "c": "transmissiya-i-kpp"}, {"s": "tolshchina-ramy-kamaz", "t": "Толщина рамы КАМАЗ: размеры, маркировка, допуски износа", "i": "📋", "c": "modeli-i-kharakteristiki"}, {"s": "tormoznaya-sistema-kamaz-43118-evro-4-skhema-tsvetnaya-s-opisaniem", "t": "Пневмосхема тормозов КАМАЗ 43118 Евро-4: описание узлов и диагностика", "i": "🛑", "c": "tormoznaya-sistema"}, {"s": "tormoznaya-sistema-kamaz-43253", "t": "Тормозная система Камаз 43253: устройство, схема и ремонт", "i": "🛑", "c": "tormoznaya-sistema"}, {"s": "toplivnaya-rampa-kamaz-evro-4", "t": "Топливная рампа Камаз Евро 4: устройство, диагностика и ремонт", "i": "⚙️", "c": "dvigatel-i-tnvd"}, {"s": "toplivnaya-sistema-kamaz-evro-2-skhema", "t": "Топливная система Камаз Евро 2: устройство, схема и диагностика ТНВД", "i": "⚙️", "c": "dvigatel-i-tnvd"}, {"s": "toplivnyj-nasos-kamaz-evro", "t": "Топливный насос Камаз Евро: диагностика, устройство и замена", "i": "⚙️", "c": "dvigatel-i-tnvd"}, {"s": "tormoznaya-lyagushka-kamaz-4310", "t": "Тормозная лягушка КАМАЗ 4310: устройство, регулировка и замена", "i": "🛑", "c": "tormoznaya-sistema"}, {"s": "to-kamaz-43118", "t": "Техническое обслуживание ТО КамАЗ 43118: регламент, нормы и этапы", "i": "📋", "c": "modeli-i-kharakteristiki"}]