[{"s": "znachki-na-pribornoj-paneli-kamaz", "t": "Значки на приборной панели КАМАЗ: расшифровка индикаторов и коды ошибок", "i": "💻", "c": "diagnostika-i-oshibki"}, {"s": "znachki-na-paneli-kamaz", "t": "Значки на панели Камаз: расшифровка индикаторов и устранение неисправностей", "i": "💻", "c": "diagnostika-i-oshibki"}, {"s": "znachki-na-paneli-priborov-kamaz-5490", "t": "Значки на панели приборов КАМАЗ 5490: расшифровка и устранение неисправностей", "i": "⚡", "c": "elektrooborudovanie"}, {"s": "znachki-na-paneli-priborov-kamaz-43118", "t": "Значки на панели приборов КАМАЗ 43118: расшифровка и поиск неисправностей", "i": "⚡", "c": "elektrooborudovanie"}, {"s": "znachki-na-pribornoj-paneli-kamaz-43118", "t": "Значки на приборной панели КАМАЗ 43118: расшифровка и устранение", "i": "⚡", "c": "elektrooborudovanie"}, {"s": "znachenie-slova-kamaz", "t": "Что означает слово КАМАЗ: история, расшифровка и характеристики", "i": "📋", "c": "modeli-i-kharakteristiki"}]